{
	"$schema": "http://schema.management.azure.com/schemas/2015-01-01/deploymentTemplate.json#",
	"contentVersion": "1.0.0.0",
	"parameters": {
		"factoryName": {
			"type": "string",
			"metadata": "Data Factory name",
			"defaultValue": "adf-MexicoToySales"
		},
		"ds_ablob_rawdata_connectionString": {
			"type": "secureString",
			"metadata": "Secure string for 'connectionString' of 'ds_ablob_rawdata'"
		},
		"ls_ablob_dataset_connectionString": {
			"type": "secureString",
			"metadata": "Secure string for 'connectionString' of 'ls_ablob_dataset'"
		},
		"ls_ablob_rawdata_connectionString": {
			"type": "secureString",
			"metadata": "Secure string for 'connectionString' of 'ls_ablob_rawdata'"
		},
		"ls_adls_rawdata_accountKey": {
			"type": "secureString",
			"metadata": "Secure string for 'accountKey' of 'ls_adls_rawdata'"
		},
		"ls_adls_rawdata_properties_typeProperties_url": {
			"type": "string",
			"defaultValue": "https://adfpipelineadls.dfs.core.windows.net/"
		}
	},
	"variables": {
		"factoryId": "[concat('Microsoft.DataFactory/factories/', parameters('factoryName'))]"
	},
	"resources": [
		{
			"name": "[concat(parameters('factoryName'), '/ds_ablob_rawdata')]",
			"type": "Microsoft.DataFactory/factories/linkedServices",
			"apiVersion": "2018-06-01",
			"properties": {
				"annotations": [],
				"type": "AzureBlobStorage",
				"typeProperties": {
					"connectionString": "[parameters('ds_ablob_rawdata_connectionString')]"
				}
			},
			"dependsOn": []
		},
		{
			"name": "[concat(parameters('factoryName'), '/ls_ablob_dataset')]",
			"type": "Microsoft.DataFactory/factories/linkedServices",
			"apiVersion": "2018-06-01",
			"properties": {
				"annotations": [],
				"type": "AzureBlobStorage",
				"typeProperties": {
					"connectionString": "[parameters('ls_ablob_dataset_connectionString')]"
				}
			},
			"dependsOn": []
		},
		{
			"name": "[concat(parameters('factoryName'), '/ls_ablob_rawdata')]",
			"type": "Microsoft.DataFactory/factories/linkedServices",
			"apiVersion": "2018-06-01",
			"properties": {
				"annotations": [],
				"type": "AzureBlobStorage",
				"typeProperties": {
					"connectionString": "[parameters('ls_ablob_rawdata_connectionString')]"
				}
			},
			"dependsOn": []
		},
		{
			"name": "[concat(parameters('factoryName'), '/ls_adls_rawdata')]",
			"type": "Microsoft.DataFactory/factories/linkedServices",
			"apiVersion": "2018-06-01",
			"properties": {
				"annotations": [],
				"type": "AzureBlobFS",
				"typeProperties": {
					"url": "[parameters('ls_adls_rawdata_properties_typeProperties_url')]",
					"accountKey": {
						"type": "SecureString",
						"value": "[parameters('ls_adls_rawdata_accountKey')]"
					}
				}
			},
			"dependsOn": []
		},
		{
			"name": "[concat(parameters('factoryName'), '/ds_ablob_rawdata')]",
			"type": "Microsoft.DataFactory/factories/datasets",
			"apiVersion": "2018-06-01",
			"properties": {
				"linkedServiceName": {
					"referenceName": "ls_ablob_rawdata",
					"type": "LinkedServiceReference"
				},
				"annotations": [],
				"type": "DelimitedText",
				"typeProperties": {
					"location": {
						"type": "AzureBlobStorageLocation",
						"container": "rawdatasets"
					},
					"columnDelimiter": ",",
					"escapeChar": "\\",
					"quoteChar": "\""
				},
				"schema": [
					{
						"type": "String"
					},
					{
						"type": "String"
					},
					{
						"type": "String"
					}
				]
			},
			"dependsOn": [
				"[concat(variables('factoryId'), '/linkedServices/ls_ablob_rawdata')]"
			]
		},
		{
			"name": "[concat(parameters('factoryName'), '/ds_adls_processdata_products')]",
			"type": "Microsoft.DataFactory/factories/datasets",
			"apiVersion": "2018-06-01",
			"properties": {
				"linkedServiceName": {
					"referenceName": "ls_adls_rawdata",
					"type": "LinkedServiceReference"
				},
				"annotations": [],
				"type": "DelimitedText",
				"typeProperties": {
					"location": {
						"type": "AzureBlobFSLocation",
						"fileName": "product.csv",
						"fileSystem": "processdata"
					},
					"columnDelimiter": ",",
					"escapeChar": "\\",
					"quoteChar": "\""
				},
				"schema": []
			},
			"dependsOn": [
				"[concat(variables('factoryId'), '/linkedServices/ls_adls_rawdata')]"
			]
		},
		{
			"name": "[concat(parameters('factoryName'), '/ds_adls_prodcuts')]",
			"type": "Microsoft.DataFactory/factories/datasets",
			"apiVersion": "2018-06-01",
			"properties": {
				"linkedServiceName": {
					"referenceName": "ls_adls_rawdata",
					"type": "LinkedServiceReference"
				},
				"annotations": [],
				"type": "DelimitedText",
				"typeProperties": {
					"location": {
						"type": "AzureBlobFSLocation",
						"fileName": "products.csv",
						"fileSystem": "rawdata"
					},
					"columnDelimiter": ",",
					"escapeChar": "\\",
					"firstRowAsHeader": true,
					"quoteChar": "\""
				},
				"schema": [
					{
						"name": "Product_ID",
						"type": "String"
					},
					{
						"name": "Product_Name",
						"type": "String"
					},
					{
						"name": "Product_Category",
						"type": "String"
					},
					{
						"name": "Product_Cost",
						"type": "String"
					},
					{
						"name": "Product_Price",
						"type": "String"
					}
				]
			},
			"dependsOn": [
				"[concat(variables('factoryId'), '/linkedServices/ls_adls_rawdata')]"
			]
		},
		{
			"name": "[concat(parameters('factoryName'), '/ds_adls_rawdata')]",
			"type": "Microsoft.DataFactory/factories/datasets",
			"apiVersion": "2018-06-01",
			"properties": {
				"linkedServiceName": {
					"referenceName": "ls_adls_rawdata",
					"type": "LinkedServiceReference"
				},
				"annotations": [],
				"type": "DelimitedText",
				"typeProperties": {
					"location": {
						"type": "AzureBlobFSLocation",
						"fileSystem": "rawdata"
					},
					"columnDelimiter": ",",
					"escapeChar": "\\",
					"firstRowAsHeader": true,
					"quoteChar": "\""
				},
				"schema": []
			},
			"dependsOn": [
				"[concat(variables('factoryId'), '/linkedServices/ls_adls_rawdata')]"
			]
		},
		{
			"name": "[concat(parameters('factoryName'), '/Ingest_toySales_data')]",
			"type": "Microsoft.DataFactory/factories/pipelines",
			"apiVersion": "2018-06-01",
			"properties": {
				"activities": [
					{
						"name": "Copy rawData to ADLS",
						"type": "Copy",
						"dependsOn": [],
						"policy": {
							"timeout": "0.12:00:00",
							"retry": 0,
							"retryIntervalInSeconds": 30,
							"secureOutput": false,
							"secureInput": false
						},
						"userProperties": [],
						"typeProperties": {
							"source": {
								"type": "DelimitedTextSource",
								"storeSettings": {
									"type": "AzureBlobStorageReadSettings",
									"recursive": true,
									"wildcardFileName": "*.csv",
									"enablePartitionDiscovery": false
								},
								"formatSettings": {
									"type": "DelimitedTextReadSettings"
								}
							},
							"sink": {
								"type": "DelimitedTextSink",
								"storeSettings": {
									"type": "AzureBlobFSWriteSettings"
								},
								"formatSettings": {
									"type": "DelimitedTextWriteSettings",
									"quoteAllText": true,
									"fileExtension": ".txt"
								}
							},
							"enableStaging": false,
							"translator": {
								"type": "TabularTranslator",
								"typeConversion": true,
								"typeConversionSettings": {
									"allowDataTruncation": true,
									"treatBooleanAsNumber": false
								}
							}
						},
						"inputs": [
							{
								"referenceName": "ds_ablob_rawdata",
								"type": "DatasetReference",
								"parameters": {}
							}
						],
						"outputs": [
							{
								"referenceName": "ds_adls_rawdata",
								"type": "DatasetReference",
								"parameters": {}
							}
						]
					}
				],
				"policy": {
					"elapsedTimeMetric": {},
					"cancelAfter": {}
				},
				"annotations": []
			},
			"dependsOn": [
				"[concat(variables('factoryId'), '/datasets/ds_ablob_rawdata')]",
				"[concat(variables('factoryId'), '/datasets/ds_adls_rawdata')]"
			]
		},
		{
			"name": "[concat(parameters('factoryName'), '/data_cleaning_transformation')]",
			"type": "Microsoft.DataFactory/factories/dataflows",
			"apiVersion": "2018-06-01",
			"properties": {
				"type": "MappingDataFlow",
				"typeProperties": {
					"sources": [
						{
							"dataset": {
								"referenceName": "ds_adls_prodcuts",
								"type": "DatasetReference"
							},
							"name": "getProducts"
						}
					],
					"sinks": [
						{
							"dataset": {
								"referenceName": "ds_adls_processdata_products",
								"type": "DatasetReference"
							},
							"name": "processdata"
						}
					],
					"transformations": [
						{
							"name": "removeNullValues"
						},
						{
							"name": "replacenulls"
						}
					],
					"scriptLines": [
						"source(output(",
						"          Product_ID as string,",
						"          Product_Name as string,",
						"          Product_Category as string,",
						"          Product_Cost as string,",
						"          Product_Price as string",
						"     ),",
						"     allowSchemaDrift: true,",
						"     validateSchema: false,",
						"     ignoreNoFilesFound: false) ~> getProducts",
						"getProducts filter(not(((isNull(Product_ID)) || isNull(Product_Name) || Product_ID==\"\" || Product_Name==\"\"))) ~> removeNullValues",
						"removeNullValues derive(Product_Cost = iif(isNull(Product_Cost), \"0\", Product_Cost)) ~> replacenulls",
						"replacenulls sink(allowSchemaDrift: true,",
						"     validateSchema: false,",
						"     filePattern:'products.csv',",
						"     umask: 0022,",
						"     preCommands: [],",
						"     postCommands: [],",
						"     skipDuplicateMapInputs: true,",
						"     skipDuplicateMapOutputs: true) ~> processdata"
					]
				}
			},
			"dependsOn": [
				"[concat(variables('factoryId'), '/datasets/ds_adls_prodcuts')]",
				"[concat(variables('factoryId'), '/datasets/ds_adls_processdata_products')]"
			]
		},
		{
			"name": "[concat(parameters('factoryName'), '/pipeline1')]",
			"type": "Microsoft.DataFactory/factories/pipelines",
			"apiVersion": "2018-06-01",
			"properties": {
				"activities": [
					{
						"name": "data_cleaning_transformation",
						"type": "ExecuteDataFlow",
						"dependsOn": [],
						"policy": {
							"timeout": "0.12:00:00",
							"retry": 0,
							"retryIntervalInSeconds": 30,
							"secureOutput": false,
							"secureInput": false
						},
						"userProperties": [],
						"typeProperties": {
							"dataflow": {
								"referenceName": "data_cleaning_transformation",
								"type": "DataFlowReference",
								"parameters": {},
								"datasetParameters": {
									"getProducts": {},
									"processdata": {}
								}
							},
							"staging": {},
							"compute": {
								"coreCount": 8,
								"computeType": "General"
							},
							"traceLevel": "Fine"
						}
					}
				],
				"policy": {
					"elapsedTimeMetric": {},
					"cancelAfter": {}
				},
				"annotations": []
			},
			"dependsOn": [
				"[concat(variables('factoryId'), '/dataflows/data_cleaning_transformation')]"
			]
		}
	]
}